PPMSplot/__init__.py
PPMSplot/__main__.py
PPMSplot/parser.py
PPMSplot/generate_config/__init__.py
PPMSplot/generate_config/__main__.py
PPMSplot-0.1.2.dist-info/METADATA
PPMSplot-0.1.2.dist-info/RECORD
PPMSplot-0.1.2.dist-info/WHEEL
PPMSplot-0.1.2.dist-info/entry_points.txt
PPMSplot-0.1.2.dist-info/top_level.txt
